{"swagger":"2.0","info":{"title":"customer-api"},"host":"localhost:8080","basePath":"/","tags":[{"name":"customer-controller","description":"Customer Controller"}],"paths":{"/api/customers":{"get":{"tags":["customer-controller"],"summary":"getAllCustomers","operationId":"getAllCustomersUsingGET","produces":["*/*"],"responses":{"200":{"description":"OK","schema":{"type":"array","items":{"$ref":"#/definitions/CustomerDto"}}}}},"post":{"tags":["customer-controller"],"summary":"createCustomer","operationId":"createCustomerUsingPOST","consumes":["application/json"],"produces":["*/*"],"parameters":[{"in":"body","name":"createCustomerRequest","description":"createCustomerRequest","required":true,"schema":{"$ref":"#/definitions/CreateCustomerRequest"}}],"responses":{"201":{"description":"Created","schema":{"$ref":"#/definitions/CustomerDto"}}}}},"/api/customers/{id}":{"get":{"tags":["customer-controller"],"summary":"getCustomerById","operationId":"getCustomerByIdUsingGET","produces":["*/*"],"parameters":[{"name":"id","in":"path","description":"id","required":true,"type":"integer","format":"int64"}],"responses":{"200":{"description":"OK","schema":{"$ref":"#/definitions/CustomerDto"}}}},"put":{"tags":["customer-controller"],"summary":"updateCustomer","operationId":"updateCustomerUsingPUT","consumes":["application/json"],"produces":["*/*"],"parameters":[{"name":"id","in":"path","description":"id","required":true,"type":"integer","format":"int64"},{"in":"body","name":"updateCustomerRequest","description":"updateCustomerRequest","required":true,"schema":{"$ref":"#/definitions/UpdateCustomerRequest"}}],"responses":{"200":{"description":"OK","schema":{"$ref":"#/definitions/CustomerDto"}}}},"delete":{"tags":["customer-controller"],"summary":"deleteCustomer","operationId":"deleteCustomerUsingDELETE","produces":["*/*"],"parameters":[{"name":"id","in":"path","description":"id","required":true,"type":"integer","format":"int64"}],"responses":{"200":{"description":"OK","schema":{"$ref":"#/definitions/CustomerDto"}}}}}},"definitions":{"CreateCustomerRequest":{"type":"object","properties":{"firstName":{"type":"string","example":"Ivan"},"lastName":{"type":"string","example":"Franchin"}},"title":"CreateCustomerRequest"},"CustomerDto":{"type":"object","properties":{"firstName":{"type":"string"},"id":{"type":"integer","format":"int64"},"lastName":{"type":"string"}},"title":"CustomerDto"},"UpdateCustomerRequest":{"type":"object","properties":{"firstName":{"type":"string","example":"Ivan2"},"lastName":{"type":"string","example":"Franchin2"}},"title":"UpdateCustomerRequest"}}}